JavaWebAnquanFix1/README.md
JavaWebAnquanFix1/__init__.py
JavaWebAnquanFix1/__main__.py
JavaWebAnquanFix1/file.epub
JavaWebAnquanFix1/index.html
JavaWebAnquanFix1/css/__init__.py
JavaWebAnquanFix1/css/annotations.css
JavaWebAnquanFix1/css/main.css
JavaWebAnquanFix1/css/normalize.css
JavaWebAnquanFix1/css/popup.css
JavaWebAnquanFix1/font/__init__.py
JavaWebAnquanFix1/font/fontello.eot
JavaWebAnquanFix1/font/fontello.svg
JavaWebAnquanFix1/font/fontello.ttf
JavaWebAnquanFix1/font/fontello.woff
JavaWebAnquanFix1/img/__init__.py
JavaWebAnquanFix1/img/annotator-glyph-sprite.png
JavaWebAnquanFix1/img/annotator-icon-sprite.png
JavaWebAnquanFix1/img/apple-touch-icon.png
JavaWebAnquanFix1/img/cancelfullscreen.png
JavaWebAnquanFix1/img/close.png
JavaWebAnquanFix1/img/fullscreen.png
JavaWebAnquanFix1/img/loader.gif
JavaWebAnquanFix1/img/menu-icon.png
JavaWebAnquanFix1/img/save.png
JavaWebAnquanFix1/img/saved.png
JavaWebAnquanFix1/img/settings-s.png
JavaWebAnquanFix1/img/settings.png
JavaWebAnquanFix1/img/star.png
JavaWebAnquanFix1/js/__init__.py
JavaWebAnquanFix1/js/epub.js
JavaWebAnquanFix1/js/epub.min.js
JavaWebAnquanFix1/js/epub.min.map
JavaWebAnquanFix1/js/hooks.min.js
JavaWebAnquanFix1/js/hooks.min.map
JavaWebAnquanFix1/js/reader.js
JavaWebAnquanFix1/js/reader.js.map
JavaWebAnquanFix1/js/reader.min.js
JavaWebAnquanFix1/js/reader.min.map
JavaWebAnquanFix1/js/hooks/__init__.py
JavaWebAnquanFix1/js/hooks/extensions/__init__.py
JavaWebAnquanFix1/js/hooks/extensions/highlight.js
JavaWebAnquanFix1/js/libs/__init__.py
JavaWebAnquanFix1/js/libs/jquery.min.js
JavaWebAnquanFix1/js/libs/localforage.min.js
JavaWebAnquanFix1/js/libs/screenfull.js
JavaWebAnquanFix1/js/libs/screenfull.min.js
JavaWebAnquanFix1/js/libs/zip.min.js
JavaWebAnquanFix1/js/plugins/__init__.py
JavaWebAnquanFix1/js/plugins/hypothesis.js
JavaWebAnquanFix1/js/plugins/search.js
java_web_anquan_fix1-2025.3.24.0.dist-info/METADATA
java_web_anquan_fix1-2025.3.24.0.dist-info/WHEEL
java_web_anquan_fix1-2025.3.24.0.dist-info/entry_points.txt
java_web_anquan_fix1-2025.3.24.0.dist-info/top_level.txt
java_web_anquan_fix1-2025.3.24.0.dist-info/RECORD
